{"ITEM":"4401","STOCKNO":"XARR-04V(C)","DSCRPT":"JST HOUSING","SRSNO":"XA","MPQ":"1000","PQ":"5000"}
{"ITEM":"4402","STOCKNO":"XARR-04VF","DSCRPT":"JST HOUSING-(C)","SRSNO":"XA","MPQ":"1000","PQ":"5000"}
{"ITEM":"4403","STOCKNO":"XARR-04VF(C)","DSCRPT":"JST HOUSING","SRSNO":"XA","MPQ":"1000","PQ":"5000"}
{"ITEM":"4404","STOCKNO":"XARR-04VF-E","DSCRPT":"JST HOUSING下單提供機種情報FORECAST","SRSNO":"XA","MPQ":"1000","PQ":"5000"}
{"ITEM":"4405","STOCKNO":"XARR-05V","DSCRPT":"JST HOUSING","SRSNO":"XA","MPQ":"1000","PQ":"5000"}
{"ITEM":"4406","STOCKNO":"XARR-05V-R","DSCRPT":"JST HOUSING","SRSNO":"XA","MPQ":"1000","PQ":"5000"}
{"ITEM":"4407","STOCKNO":"XARR-05VF","DSCRPT":"JST HOUSING","SRSNO":"XA","MPQ":"1000","PQ":"5000"}
{"ITEM":"4408","STOCKNO":"XARR-06V","DSCRPT":"JST HOUSING","SRSNO":"XA","MPQ":"500","PQ":"2500"}
{"ITEM":"4409","STOCKNO":"XARR-06VF","DSCRPT":"JST HOUSING","SRSNO":"XA","MPQ":"500","PQ":"2500"}
{"ITEM":"4410","STOCKNO":"XARR-06VF-R","DSCRPT":"JST HOUSING","SRSNO":"XA","MPQ":"500","PQ":"2500"}
{"ITEM":"4411","STOCKNO":"XARR-07V","DSCRPT":"JST HOUSING(P)","SRSNO":"XA","MPQ":"500","PQ":"2500"}
{"ITEM":"4412","STOCKNO":"XARR-07V(P)","DSCRPT":"JST HOUSING","SRSNO":"XA","MPQ":"500","PQ":"2500"}
{"ITEM":"4413","STOCKNO":"XARR-07V(P)","DSCRPT":"JST HOUSING","SRSNO":"XA","MPQ":"500","PQ":"2500"}
{"ITEM":"4414","STOCKNO":"XARR-08V","DSCRPT":"JST HOUSING","SRSNO":"XA","MPQ":"500","PQ":"2500"}
{"ITEM":"4415","STOCKNO":"XARR-08V-WGT4","DSCRPT":"JST HOUSING","SRSNO":"XA","MPQ":"500","PQ":"2500"}
{"ITEM":"4416","STOCKNO":"XARR-08VF","DSCRPT":"JST HOUSING","SRSNO":"XA","MPQ":"500","PQ":"2500"}
{"ITEM":"4417","STOCKNO":"XARR-09V","DSCRPT":"JST HOUSING","SRSNO":"XA","MPQ":"500","PQ":"2500"}
{"ITEM":"4418","STOCKNO":"XARR-09VF","DSCRPT":"JST HOUSING","SRSNO":"XA","MPQ":"500","PQ":"2500"}
{"ITEM":"4419","STOCKNO":"XARR-10V","DSCRPT":"JST HOUSING","SRSNO":"XA","MPQ":"500","PQ":"2000"}
{"ITEM":"4420","STOCKNO":"XARR-10VF","DSCRPT":"JST HOUSING","SRSNO":"XA","MPQ":"500","PQ":"2000"}
{"ITEM":"4421","STOCKNO":"XARR-11V","DSCRPT":"JST HOUSING","SRSNO":"XA","MPQ":"500","PQ":"2000"}
{"ITEM":"4422","STOCKNO":"XARR-11V-WGT4","DSCRPT":"JST HOUSING","SRSNO":"XA","MPQ":"500","PQ":"2000"}
{"ITEM":"4423","STOCKNO":"XARR-12V","DSCRPT":"JST HOUSING","SRSNO":"XA","MPQ":"500","PQ":"2000"}
{"ITEM":"4424","STOCKNO":"XARR-12VF","DSCRPT":"JST HOUSING","SRSNO":"XA","MPQ":"500","PQ":"2000"}
{"ITEM":"4425","STOCKNO":"XARR-13V","DSCRPT":"JST HOUSING","SRSNO":"XA","MPQ":"500","PQ":"2000"}
{"ITEM":"4426","STOCKNO":"XARR-14V","DSCRPT":"JST HOUSING","SRSNO":"XA","MPQ":"500","PQ":"2000"}
{"ITEM":"4427","STOCKNO":"XARR-15V","DSCRPT":"JST HOUSING","SRSNO":"XA","MPQ":"500","PQ":"2000"}
{"ITEM":"4428","STOCKNO":"XCC-04V-A1-STO-187-110-K","DSCRPT":"JST BASE","SRSNO":"XCC","MPQ":"1000","PQ":"1000"}
{"ITEM":"4429","STOCKNO":"XCC-HC21SR-S532-N1501(LF)(SN)","DSCRPT":"JST BASE","SRSNO":"XCC","MPQ":"520","PQ":"1040"}
{"ITEM":"4430","STOCKNO":"XCC-HC21SR-S532-R1101(LF)(SN)","DSCRPT":"JST BASE","SRSNO":"XCC","MPQ":"520","PQ":"1040"}
{"ITEM":"4431","STOCKNO":"XCC-HC21SR-S532-R1201(LF)(SN)","DSCRPT":"JST BASE","SRSNO":"XCC","MPQ":"1040","PQ":"1040"}
{"ITEM":"4432","STOCKNO":"XHP-02-SB","DSCRPT":"JST HOUSING","SRSNO":"XH","MPQ":"1000","PQ":"30000"}
{"ITEM":"4433","STOCKNO":"XHP-1","DSCRPT":"JST HOUSING-(P)","SRSNO":"XH","MPQ":"1000","PQ":"30000"}
{"ITEM":"4434","STOCKNO":"XHP-1(P)","DSCRPT":"JST HOUSING","SRSNO":"XH","MPQ":"1000","PQ":"30000"}
{"ITEM":"4435","STOCKNO":"XHP-10","DSCRPT":"JST HOUSING","SRSNO":"XH","MPQ":"1000","PQ":"10000"}
{"ITEM":"4436","STOCKNO":"XHP-10-BK","DSCRPT":"JST HOUSING","SRSNO":"XH","MPQ":"1000","PQ":"10000"}
{"ITEM":"4437","STOCKNO":"XHP-10-E","DSCRPT":"JST HOUSING","SRSNO":"XH","MPQ":"10000","PQ":"10000"}
{"ITEM":"4438","STOCKNO":"XHP-10-R","DSCRPT":"JST HOUSING","SRSNO":"XH","MPQ":"1000","PQ":"10000"}
{"ITEM":"4439","STOCKNO":"XHP-11","DSCRPT":"JST HOUSING","SRSNO":"XH","MPQ":"1000","PQ":"10000"}
{"ITEM":"4440","STOCKNO":"XHP-11(P)","DSCRPT":"JST HOUSING","SRSNO":"XH","MPQ":"1000","PQ":"10000"}
{"ITEM":"4441","STOCKNO":"XHP-12","DSCRPT":"JST HOUSING","SRSNO":"XH","MPQ":"1000","PQ":"5000"}
{"ITEM":"4442","STOCKNO":"XHP-13","DSCRPT":"JST HOUSING","SRSNO":"XH","MPQ":"1000","PQ":"5000"}
{"ITEM":"4443","STOCKNO":"XHP-14","DSCRPT":"JST HOUSING","SRSNO":"XH","MPQ":"1000","PQ":"5000"}
{"ITEM":"4444","STOCKNO":"XHP-14(P)","DSCRPT":"JST HOUSING","SRSNO":"XH","MPQ":"1000","PQ":"5000"}
{"ITEM":"4445","STOCKNO":"XHP-15","DSCRPT":"JST HOUSING(P)","SRSNO":"XH","MPQ":"1000","PQ":"5000"}
{"ITEM":"4446","STOCKNO":"XHP-15(P)","DSCRPT":"JST HOUSING","SRSNO":"XH","MPQ":"1000","PQ":"5000"}
{"ITEM":"4447","STOCKNO":"XHP-16","DSCRPT":"JST HOUSING","SRSNO":"XH","MPQ":"1000","PQ":"5000"}
{"ITEM":"4448","STOCKNO":"XHP-2","DSCRPT":"JST HOUSING","SRSNO":"XH","MPQ":"1000","PQ":"30000"}
{"ITEM":"4449","STOCKNO":"XHP-2 BK","DSCRPT":"JST HOUSING(原廠)","SRSNO":"XH","MPQ":"1000","PQ":"30000"}
{"ITEM":"4450","STOCKNO":"XHP-2(10.0)-U(P)","DSCRPT":"JST HOUSING","SRSNO":"XH","MPQ":"20000","PQ":"20000"}
