{"ITEM":"201","STOCKNO":"03RSX-D0.38S-5AX-KOC(LF)(SN)","DSCRPT":"JST BASE","MPQ":"700","PQ":"8400"}
{"ITEM":"202","STOCKNO":"03RSX-D0.38S-GA-1(LF)(SN)","DSCRPT":"JST BASE","MPQ":"8400","PQ":"8400"}
{"ITEM":"203","STOCKNO":"03RSX-D0.38S-GA-5AX-KOC(LF)(SN)","DSCRPT":"JST BASE","MPQ":"8400","PQ":"8400"}
{"ITEM":"204","STOCKNO":"03RSXA-D0.38S-E-KAD(LF)(SN)","DSCRPT":"JST BASE","MPQ":"8400","PQ":"8400"}
{"ITEM":"205","STOCKNO":"03SR-3S","DSCRPT":"JST HOUSING","MPQ":"2000","PQ":"48000"}
{"ITEM":"206","STOCKNO":"03SSR-32H","DSCRPT":"JST HOUSING","MPQ":"2000","PQ":"48000"}
{"ITEM":"207","STOCKNO":"03SSR-32K(HF)","DSCRPT":"JST HOUSING","MPQ":"48000","PQ":"48000"}
{"ITEM":"208","STOCKNO":"03SUR-32S","DSCRPT":"JST HOUSING","MPQ":"2000","PQ":"48000"}
{"ITEM":"209","STOCKNO":"03SZ-3W","DSCRPT":"JST HOUSING","MPQ":"48000","PQ":"48000"}
{"ITEM":"210","STOCKNO":"03T-JWPF-VKLE-S","DSCRPT":"JST HOUSING","MPQ":"1000","PQ":"5000"}
{"ITEM":"211","STOCKNO":"03T-JWPF-VRLE-S","DSCRPT":"JST HOUSING","MPQ":"1000","PQ":"5000"}
{"ITEM":"212","STOCKNO":"03T-JWPF-VSLE-S","DSCRPT":"JST HOUSING","MPQ":"1000","PQ":"5000"}
{"ITEM":"213","STOCKNO":"03T-JWPF-VSM-SK","DSCRPT":"JST HOUSING","MPQ":"1000","PQ":"3000"}
{"ITEM":"214","STOCKNO":"03T-WPJV-1-SM","DSCRPT":"JST HOUSING","MPQ":"495","PQ":"1980"}
{"ITEM":"215","STOCKNO":"03T-WPJV-2-RM","DSCRPT":"JST HOUSING","MPQ":"495","PQ":"1980"}
{"ITEM":"216","STOCKNO":"03VR-2R(LF)(SN)","DSCRPT":"JST BASE","MPQ":"1000","PQ":"5000"}
{"ITEM":"217","STOCKNO":"03VR-AN(LF)(SN)","DSCRPT":"JST HOUSING","MPQ":"1000","PQ":"5000"}
{"ITEM":"218","STOCKNO":"03VR-BO","DSCRPT":"JST HOUSING","MPQ":"1000","PQ":"5000"}
{"ITEM":"219","STOCKNO":"03VR-BO(LF)(SN)","DSCRPT":"JST HOUSING","MPQ":"1000","PQ":"5000"}
{"ITEM":"220","STOCKNO":"03XR-6E-P","DSCRPT":"JST HOUSING","MPQ":"2000","PQ":"48000"}
{"ITEM":"221","STOCKNO":"03XR-6H-P","DSCRPT":"JST HOUSING","MPQ":"2000","PQ":"48000"}
{"ITEM":"222","STOCKNO":"03XR-6H-P(N)","DSCRPT":"JST HOUSING","MPQ":"2000","PQ":"48000"}
{"ITEM":"223","STOCKNO":"03XR-6Y-P","DSCRPT":"JST HOUSING","MPQ":"2000","PQ":"48000"}
{"ITEM":"224","STOCKNO":"03XR-6Y-P(N)","DSCRPT":"JST HOUSING","MPQ":"2000","PQ":"48000"}
{"ITEM":"225","STOCKNO":"03ZA-8M(LF)(SN)","DSCRPT":"JST HOUSING","MPQ":"2000","PQ":"48000"}
{"ITEM":"226","STOCKNO":"03ZR-3H","DSCRPT":"JST HOUSING","MPQ":"2000","PQ":"48000"}
{"ITEM":"227","STOCKNO":"03ZR-3H-P","DSCRPT":"JST HOUSING","MPQ":"2000","PQ":"48000"}
{"ITEM":"228","STOCKNO":"03ZR-8M","DSCRPT":"JST HOUSING","MPQ":"2000","PQ":"48000"}
{"ITEM":"229","STOCKNO":"03ZR-8M-P","DSCRPT":"JST HOUSING","MPQ":"2000","PQ":"48000"}
{"ITEM":"230","STOCKNO":"04(1.0)9FLH-RSM1-GB-TB(LF)(SN)","DSCRPT":"JST BASE","MPQ":"3000","PQ":"18000"}
{"ITEM":"231","STOCKNO":"04(1.0)9FLH-RSM1-TB(LF)(SN)","DSCRPT":"JST BASE","MPQ":"3000","PQ":"18000"}
{"ITEM":"232","STOCKNO":"04(1.0)9FLH-SM1-TB(LF)(SN)","DSCRPT":"JST BASE","MPQ":"3000","PQ":"18000"}
{"ITEM":"233","STOCKNO":"04(1.0)FHA-SM1-GAN-AL-ETB(HF)","DSCRPT":"JST BASE","MPQ":"7000","PQ":"63000"}
{"ITEM":"234","STOCKNO":"04(5.0)JQ-BT(LF)(SN)","DSCRPT":"JST BASE","MPQ":"6000","PQ":"6000"}
{"ITEM":"235","STOCKNO":"04ASR-30S","DSCRPT":"JST HOUSING","MPQ":"3000","PQ":"72000"}
{"ITEM":"236","STOCKNO":"04BR-6S","DSCRPT":"JST HOUSING","MPQ":"1000","PQ":"18000"}
{"ITEM":"237","STOCKNO":"04CK-6H-P","DSCRPT":"JST HOUSING","MPQ":"48000","PQ":"48000"}
{"ITEM":"238","STOCKNO":"04CK-6H-PC","DSCRPT":"JST HOUSING","MPQ":"48000","PQ":"48000"}
{"ITEM":"239","STOCKNO":"04CPT-B1-2A","DSCRPT":"JST HOUSING","MPQ":"7200","PQ":"7200"}
{"ITEM":"240","STOCKNO":"04CPT-B1-2B","DSCRPT":"JST HOUSING","MPQ":"7200","PQ":"7200"}
{"ITEM":"241","STOCKNO":"04CR-6H-P","DSCRPT":"JST HOUSING(P)","MPQ":"2000","PQ":"48000"}
{"ITEM":"242","STOCKNO":"04CR-6H-P(P)","DSCRPT":"JST HOUSING","MPQ":"2000","PQ":"48000"}
{"ITEM":"243","STOCKNO":"04CZ-6H(P)","DSCRPT":"JST HOUSING","MPQ":"48000","PQ":"48000"}
{"ITEM":"244","STOCKNO":"04CZ-6Y","DSCRPT":"JST HOUSING","MPQ":"2000","PQ":"0"}
{"ITEM":"245","STOCKNO":"04CZ-6Y(P)","DSCRPT":"JST HOUSING","MPQ":"48000","PQ":"48000"}
{"ITEM":"246","STOCKNO":"04DA-6S","DSCRPT":"JST HOUSING","MPQ":"1000","PQ":"24000"}
{"ITEM":"247","STOCKNO":"04DA-6S(LF)","DSCRPT":"JST HOUSING","MPQ":"1","PQ":"24000"}
{"ITEM":"248","STOCKNO":"04DA-8M","DSCRPT":"JST HOUSING","MPQ":"1000","PQ":"24000"}
{"ITEM":"249","STOCKNO":"04DA-8M(LF)","DSCRPT":"JST HOUSING","MPQ":"24000","PQ":"24000"}
{"ITEM":"250","STOCKNO":"04DB-4K","DSCRPT":"JST HOUSING","MPQ":"1000","PQ":"18000"}
