{"ITEM":"2801","STOCKNO":"PARP-09V","DSCRPT":"JST HOUSING","SRSNO":"PA","MPQ":"1000","PQ":"5000"}
{"ITEM":"2802","STOCKNO":"PARP-10V","DSCRPT":"JST HOUSING","SRSNO":"PA","MPQ":"1000","PQ":"5000"}
{"ITEM":"2803","STOCKNO":"PARP-10V-K","DSCRPT":"JST HOUSING-¤Ułć«e¶·´Ł¨Ńľ÷şŘ±ˇłř¤ÎFORECA","SRSNO":"PA","MPQ":"1000","PQ":"5000"}
{"ITEM":"2804","STOCKNO":"PARP-11V","DSCRPT":"JST HOUSING","SRSNO":"PA","MPQ":"500","PQ":"5000"}
{"ITEM":"2805","STOCKNO":"PARP-12V","DSCRPT":"JST HOUSING","SRSNO":"PA","MPQ":"500","PQ":"5000"}
{"ITEM":"2806","STOCKNO":"PARP-13V","DSCRPT":"JST HOUSING","SRSNO":"PA","MPQ":"500","PQ":"5000"}
{"ITEM":"2807","STOCKNO":"PARP-15V","DSCRPT":"JST HOUSING","SRSNO":"PA","MPQ":"500","PQ":"4000"}
{"ITEM":"2808","STOCKNO":"PARP-15V","DSCRPT":"JST HOUSING","SRSNO":"PA","MPQ":"500","PQ":"4000"}
{"ITEM":"2809","STOCKNO":"PB-621SR13-TF","DSCRPT":"JST BASE-(TI)","SRSNO":"PB","MPQ":"2000","PQ":"12000"}
{"ITEM":"2810","STOCKNO":"PB-621SR13-TF(TI)","DSCRPT":"JST BASE","SRSNO":"PB","MPQ":"2000","PQ":"12000"}
{"ITEM":"2811","STOCKNO":"PBVP-04V-S","DSCRPT":"JST HOUSING","SRSNO":"PBV","MPQ":"2000","PQ":"20000"}
{"ITEM":"2812","STOCKNO":"PBVP-10V-S","DSCRPT":"JST HOUSING","SRSNO":"PBV","MPQ":"1000","PQ":"10000"}
{"ITEM":"2813","STOCKNO":"PBVP-12V-S","DSCRPT":"JST HOUSING","SRSNO":"PBV","MPQ":"500","PQ":"8000"}
{"ITEM":"2814","STOCKNO":"PC-1.25 F-7","DSCRPT":"JST TERMINAL","SRSNO":"FV","MPQ":"25000","PQ":"25000"}
{"ITEM":"2815","STOCKNO":"PCF-2","DSCRPT":"JST TERMINAL","SRSNO":"PC-type PCM","MPQ":"1000","PQ":"4000"}
{"ITEM":"2816","STOCKNO":"PCM-2 BU","DSCRPT":"JST TERMINAL","SRSNO":"PC-type PCM","MPQ":"500","PQ":"3000"}
{"ITEM":"2817","STOCKNO":"PHAR-14","DSCRPT":"JST HOUSING","SRSNO":"PHA","MPQ":"500","PQ":"5000"}
{"ITEM":"2818","STOCKNO":"PHDR-12VS(P)","DSCRPT":"JST HOUSING","SRSNO":"PHD","MPQ":"1000","PQ":"20000"}
{"ITEM":"2819","STOCKNO":"PHDR-14VS","DSCRPT":"JST HOUSING","SRSNO":"PHD","MPQ":"1000","PQ":"20000"}
{"ITEM":"2820","STOCKNO":"PHDR-16VS","DSCRPT":"JST HOUSING","SRSNO":"PHD","MPQ":"1000","PQ":"10000"}
{"ITEM":"2821","STOCKNO":"PHDR-22VS","DSCRPT":"JST HOUSING-(P)","SRSNO":"PHD","MPQ":"1000","PQ":"10000"}
{"ITEM":"2822","STOCKNO":"PHDR-22VS(P)","DSCRPT":"JST HOUSING","SRSNO":"PHD","MPQ":"1000","PQ":"10000"}
{"ITEM":"2823","STOCKNO":"PHNR-02-H","DSCRPT":"JST HOUSING","SRSNO":"KR","MPQ":"1000","PQ":"30000"}
{"ITEM":"2824","STOCKNO":"PHNR-03-H","DSCRPT":"JST HOUSING","SRSNO":"KR","MPQ":"1000","PQ":"30000"}
{"ITEM":"2825","STOCKNO":"PHNR-04-H","DSCRPT":"JST HOUSING","SRSNO":"KR","MPQ":"30000","PQ":"30000"}
{"ITEM":"2826","STOCKNO":"PHNR-05-H","DSCRPT":"JST HOSING","SRSNO":"KR","MPQ":"1000","PQ":"20000"}
{"ITEM":"2827","STOCKNO":"PHNR-06-H","DSCRPT":"JST HOUSING","SRSNO":"PHN","MPQ":"20000","PQ":"20000"}
{"ITEM":"2828","STOCKNO":"PHR-10","DSCRPT":"JST HOUSING","SRSNO":"PH","MPQ":"1000","PQ":"15000"}
{"ITEM":"2829","STOCKNO":"PHR-10(L)","DSCRPT":"JST HOUSING-µL(L)","SRSNO":"PH","MPQ":"1000","PQ":"15000"}
{"ITEM":"2830","STOCKNO":"PHR-11","DSCRPT":"JST HOUSING","SRSNO":"PH","MPQ":"1000","PQ":"15000"}
{"ITEM":"2831","STOCKNO":"PHR-11(L)","DSCRPT":"JST HOUSING-µL(L)","SRSNO":"PH","MPQ":"1000","PQ":"15000"}
{"ITEM":"2832","STOCKNO":"PHR-12","DSCRPT":"JST HOUSING","SRSNO":"PH","MPQ":"1000","PQ":"10000"}
{"ITEM":"2833","STOCKNO":"PHR-12(L)","DSCRPT":"JST HOUSING-µL(L)","SRSNO":"PH","MPQ":"1000","PQ":"10000"}
{"ITEM":"2834","STOCKNO":"PHR-14","DSCRPT":"JST HOUSING-(L)","SRSNO":"PH","MPQ":"1000","PQ":"10000"}
{"ITEM":"2835","STOCKNO":"PHR-14(L)","DSCRPT":"JST HOSING","SRSNO":"PH","MPQ":"1000","PQ":"10000"}
{"ITEM":"2836","STOCKNO":"PHR-15","DSCRPT":"JST HOUSING","SRSNO":"PH","MPQ":"1000","PQ":"10000"}
{"ITEM":"2837","STOCKNO":"PHR-15(L)","DSCRPT":"JST HOUSING-µL(L)","SRSNO":"PH","MPQ":"1000","PQ":"10000"}
{"ITEM":"2838","STOCKNO":"PHR-16","DSCRPT":"JST HOUSING","SRSNO":"PH","MPQ":"1000","PQ":"10000"}
{"ITEM":"2839","STOCKNO":"PHR-16(L)","DSCRPT":"JST HOUSING-µL(L)","SRSNO":"PH","MPQ":"1000","PQ":"10000"}
{"ITEM":"2840","STOCKNO":"PHR-2","DSCRPT":"JST HOUSING-(PP)","SRSNO":"PH","MPQ":"1000","PQ":"30000"}
{"ITEM":"2841","STOCKNO":"PHR-2(PP)","DSCRPT":"JST HOUSING","SRSNO":"PH","MPQ":"2000","PQ":"30000"}
{"ITEM":"2842","STOCKNO":"PHR-2-BK(PP)","DSCRPT":"JST HOUSING","SRSNO":"PH","MPQ":"1000","PQ":"30000"}
{"ITEM":"2843","STOCKNO":"PHR-3","DSCRPT":"JST HOUSING-(PP)","SRSNO":"PH","MPQ":"1000","PQ":"30000"}
{"ITEM":"2844","STOCKNO":"PHR-3(L)(PP)","DSCRPT":"JST HOUSING-(PP)","SRSNO":"PH","MPQ":"2000","PQ":"30000"}
{"ITEM":"2845","STOCKNO":"PHR-3(PP)","DSCRPT":"JST HOUSING-(PP)","SRSNO":"PH","MPQ":"2000","PQ":"30000"}
{"ITEM":"2846","STOCKNO":"PHR-3-BK","DSCRPT":"JST HOUSING(PP)","SRSNO":"PH","MPQ":"1000","PQ":"30000"}
{"ITEM":"2847","STOCKNO":"PHR-3-BK(PP)","DSCRPT":"JST HOUSING","SRSNO":"PH","MPQ":"1000","PQ":"30000"}
{"ITEM":"2848","STOCKNO":"PHR-4","DSCRPT":"JST HOUSING","SRSNO":"PH","MPQ":"2000","PQ":"30000"}
{"ITEM":"2849","STOCKNO":"PHR-4(L)","DSCRPT":"JST HOUSING","SRSNO":"PH","MPQ":"2000","PQ":"30000"}
{"ITEM":"2850","STOCKNO":"PHR-5","DSCRPT":"JST HOUSING-(PP)","SRSNO":"PH","MPQ":"2000","PQ":"20000"}
