{"ITEM":"4201","STOCKNO":"XAP-03V-1-K(PP)","DSCRPT":"JST HOUSING","SRSNO":"XA","MPQ":"1000","PQ":"20000"}
{"ITEM":"4202","STOCKNO":"XAP-03V-1-LE(P)","DSCRPT":"JST HOUSING","SRSNO":"XA","MPQ":"20000","PQ":"20000"}
{"ITEM":"4203","STOCKNO":"XAP-03V-1-M","DSCRPT":"JST HOUSING(PP)","SRSNO":"XA","MPQ":"1000","PQ":"20000"}
{"ITEM":"4204","STOCKNO":"XAP-03V-1-M(PP)","DSCRPT":"JST HOUSING","SRSNO":"XA","MPQ":"20000","PQ":"20000"}
{"ITEM":"4205","STOCKNO":"XAP-03V-1-N(PP)","DSCRPT":"JST HOUSING","SRSNO":"XA","MPQ":"1000","PQ":"20000"}
{"ITEM":"4206","STOCKNO":"XAP-03V-1-R(P)","DSCRPT":"JST HOUSING","SRSNO":"XA","MPQ":"1000","PQ":"20000"}
{"ITEM":"4207","STOCKNO":"XAP-03V-1-R(PP)","DSCRPT":"JST HOUSING","SRSNO":"XA","MPQ":"1000","PQ":"20000"}
{"ITEM":"4208","STOCKNO":"XAP-03V-1-Y(P)","DSCRPT":"JST HOUSING","SRSNO":"XA","MPQ":"20000","PQ":"20000"}
{"ITEM":"4209","STOCKNO":"XAP-04V-1","DSCRPT":"JST HOUSING-(L)(P)","SRSNO":"XA","MPQ":"1000","PQ":"10000"}
{"ITEM":"4210","STOCKNO":"XAP-04V-1(L)(P)","DSCRPT":"JST HOUSING","SRSNO":"XA","MPQ":"1000","PQ":"10000"}
{"ITEM":"4211","STOCKNO":"XAP-04V-1(P)","DSCRPT":"JST HOUSING-(L)(P)","SRSNO":"XA","MPQ":"1000","PQ":"10000"}
{"ITEM":"4212","STOCKNO":"XAP-04V-1-E(P)","DSCRPT":"JST HOUSINGÂĹ¦â","SRSNO":"XA","MPQ":"1000","PQ":"10000"}
{"ITEM":"4213","STOCKNO":"XAP-04V-1-K","DSCRPT":"JST HOUSING(P)","SRSNO":"XA","MPQ":"10000","PQ":"10000"}
{"ITEM":"4214","STOCKNO":"XAP-04V-1-K(P)","DSCRPT":"JST HOUSING","SRSNO":"XA","MPQ":"1000","PQ":"10000"}
{"ITEM":"4215","STOCKNO":"XAP-04V-1-K(P)","DSCRPT":"JST HOUSING","SRSNO":"XA","MPQ":"1000","PQ":"10000"}
{"ITEM":"4216","STOCKNO":"XAP-04V-1-O(P)","DSCRPT":"JST HOUSING","SRSNO":"XA","MPQ":"10000","PQ":"10000"}
{"ITEM":"4217","STOCKNO":"XAP-04V-1-R(P)","DSCRPT":"JST HOUSING","SRSNO":"XA","MPQ":"1000","PQ":"10000"}
{"ITEM":"4218","STOCKNO":"XAP-04V-1-Y","DSCRPT":"JST HOUSING(P)","SRSNO":"XA","MPQ":"1000","PQ":"10000"}
{"ITEM":"4219","STOCKNO":"XAP-04V-1-Y(P)","DSCRPT":"JST HOUSING","SRSNO":"XA","MPQ":"1000","PQ":"10000"}
{"ITEM":"4220","STOCKNO":"XAP-04V-1-Z(P)","DSCRPT":"JST HOUSING","SRSNO":"XA","MPQ":"1000","PQ":"10000"}
{"ITEM":"4221","STOCKNO":"XAP-05V-1","DSCRPT":"JST HOUSING-(P)(P)","SRSNO":"XA","MPQ":"1000","PQ":"10000"}
{"ITEM":"4222","STOCKNO":"XAP-05V-1(L)(P)","DSCRPT":"JST HOUSING","SRSNO":"XA","MPQ":"1000","PQ":"10000"}
{"ITEM":"4223","STOCKNO":"XAP-05V-1(P)","DSCRPT":"JST HOUSING-(L)(P)","SRSNO":"XA","MPQ":"1000","PQ":"10000"}
{"ITEM":"4224","STOCKNO":"XAP-05V-1-K","DSCRPT":"JST HOUSING","SRSNO":"XA","MPQ":"1000","PQ":"10000"}
{"ITEM":"4225","STOCKNO":"XAP-05V-1-K(P)","DSCRPT":"JST HOUSING","SRSNO":"XA","MPQ":"1000","PQ":"10000"}
{"ITEM":"4226","STOCKNO":"XAP-05V-1-M(P)","DSCRPT":"JST HOUSING","SRSNO":"XA","MPQ":"10000","PQ":"10000"}
{"ITEM":"4227","STOCKNO":"XAP-05V-1-R","DSCRPT":"JST HOUSING(P)","SRSNO":"XA","MPQ":"1000","PQ":"10000"}
{"ITEM":"4228","STOCKNO":"XAP-05V-1-R(P)","DSCRPT":"JST HOUSING","SRSNO":"XA","MPQ":"1000","PQ":"10000"}
{"ITEM":"4229","STOCKNO":"XAP-05V-1-Y","DSCRPT":"JST HOUSING","SRSNO":"XA","MPQ":"10000","PQ":"10000"}
{"ITEM":"4230","STOCKNO":"XAP-05V-1-Z(P)","DSCRPT":"JST HOUSING","SRSNO":"XA","MPQ":"1000","PQ":"10000"}
{"ITEM":"4231","STOCKNO":"XAP-06V-1","DSCRPT":"JST HOUSING-(P)","SRSNO":"XA","MPQ":"1000","PQ":"10000"}
{"ITEM":"4232","STOCKNO":"XAP-06V-1(P)","DSCRPT":"JST HOUSING","SRSNO":"XA","MPQ":"1000","PQ":"10000"}
{"ITEM":"4233","STOCKNO":"XAP-06V-1-E(P)","DSCRPT":"JST HOUSING","SRSNO":"XA","MPQ":"1000","PQ":"10000"}
{"ITEM":"4234","STOCKNO":"XAP-06V-1-K(P)","DSCRPT":"JST HOUSING","SRSNO":"XA","MPQ":"1000","PQ":"10000"}
{"ITEM":"4235","STOCKNO":"XAP-06V-1-M","DSCRPT":"JST HOUSING(P)","SRSNO":"XA","MPQ":"1000","PQ":"10000"}
{"ITEM":"4236","STOCKNO":"XAP-06V-1-M(P)","DSCRPT":"JST HOUSING","SRSNO":"XA","MPQ":"10000","PQ":"10000"}
{"ITEM":"4237","STOCKNO":"XAP-06V-1-R","DSCRPT":"JST HOUSING-(P)","SRSNO":"XA","MPQ":"1000","PQ":"10000"}
{"ITEM":"4238","STOCKNO":"XAP-06V-1-R(P)","DSCRPT":"JST HOUSING","SRSNO":"XA","MPQ":"1000","PQ":"10000"}
{"ITEM":"4239","STOCKNO":"XAP-06V-1-Y(P)","DSCRPT":"JST HOUSING","SRSNO":"XA","MPQ":"1000","PQ":"10000"}
{"ITEM":"4240","STOCKNO":"XAP-06V-1-Z(P)","DSCRPT":"JST HOUSING","SRSNO":"XA","MPQ":"1000","PQ":"10000"}
{"ITEM":"4241","STOCKNO":"XAP-06VM-1(P)","DSCRPT":"JST HOUSING","SRSNO":"XA","MPQ":"1000","PQ":"10000"}
{"ITEM":"4242","STOCKNO":"XAP-06VM-1-E(P)","DSCRPT":"JST HOUSING","SRSNO":"XA","MPQ":"10000","PQ":"10000"}
{"ITEM":"4243","STOCKNO":"XAP-07V-1","DSCRPT":"JST HOUSING","SRSNO":"XA","MPQ":"1000","PQ":"10000"}
{"ITEM":"4244","STOCKNO":"XAP-07V-1-E","DSCRPT":"JST HOUSING","SRSNO":"XA","MPQ":"1000","PQ":"10000"}
{"ITEM":"4245","STOCKNO":"XAP-07V-1-R","DSCRPT":"JST HOUSING","SRSNO":"XA","MPQ":"10000","PQ":"10000"}
{"ITEM":"4246","STOCKNO":"XAP-07V-1-Y","DSCRPT":"JST HOUSING","SRSNO":"XA","MPQ":"10000","PQ":"10000"}
{"ITEM":"4247","STOCKNO":"XAP-07VM-1","DSCRPT":"JST HOUSING","SRSNO":"XA","MPQ":"10000","PQ":"10000"}
{"ITEM":"4248","STOCKNO":"XAP-08V-1","DSCRPT":"JST HOUSING(P)","SRSNO":"XA","MPQ":"1000","PQ":"10000"}
{"ITEM":"4249","STOCKNO":"XAP-08V-1(P)","DSCRPT":"JST HOUSING","SRSNO":"XA","MPQ":"1000","PQ":"10000"}
{"ITEM":"4250","STOCKNO":"XAP-08V-1-K(P)","DSCRPT":"JST HOUSING","SRSNO":"XA","MPQ":"1000","PQ":"10000"}
