{"ITEM":"13351","STOCKNO":"VLP-06V","DSCRPT":"JST HOUSING","MPQ":"500","PQ":"3000"}
{"ITEM":"13352","STOCKNO":"VLP-06V-1","DSCRPT":"JST HOUSING","MPQ":"500","PQ":"3000"}
{"ITEM":"13353","STOCKNO":"VLP-06V-K","DSCRPT":"JST HOUSING","MPQ":"500","PQ":"3000"}
{"ITEM":"13354","STOCKNO":"VLP-06V-WGT4","DSCRPT":"JST HOUSING","MPQ":"500","PQ":"3000"}
{"ITEM":"13355","STOCKNO":"VLP-08V","DSCRPT":"JST HOUSING(P)","MPQ":"200","PQ":"2000"}
{"ITEM":"13356","STOCKNO":"VLP-08V(P)","DSCRPT":"JST HOUSING","MPQ":"200","PQ":"2000"}
{"ITEM":"13357","STOCKNO":"VLP-08V-1","DSCRPT":"JST HOUSING(P)","MPQ":"500","PQ":"0"}
{"ITEM":"13358","STOCKNO":"VLP-08V-1(P)","DSCRPT":"JST HOUSING","MPQ":"200","PQ":"2000"}
{"ITEM":"13359","STOCKNO":"VLP-08V-1(P)","DSCRPT":"JST HOUSING","MPQ":"200","PQ":"2000"}
{"ITEM":"13360","STOCKNO":"VLP-09V-1","DSCRPT":"JST HOUSING","MPQ":"100","PQ":"800"}
{"ITEM":"13361","STOCKNO":"VLP-12V","DSCRPT":"JST HOUSING","MPQ":"100","PQ":"1500"}
{"ITEM":"13362","STOCKNO":"VLP-12V-1","DSCRPT":"JST HOUSING","MPQ":"100","PQ":"1500"}
{"ITEM":"13363","STOCKNO":"VLR-01VF","DSCRPT":"JST HOUSING","MPQ":"500","PQ":"5000"}
{"ITEM":"13364","STOCKNO":"VLR-01VF-WG","DSCRPT":"JST HOUSING","MPQ":"500","PQ":"5000"}
{"ITEM":"13365","STOCKNO":"VLR-01VFS","DSCRPT":"JST HOUSING","MPQ":"500","PQ":"5000"}
{"ITEM":"13366","STOCKNO":"VLR-02V","DSCRPT":"JST HOUSING","MPQ":"500","PQ":"2000"}
{"ITEM":"13367","STOCKNO":"VLR-02V-K","DSCRPT":"JST HOUSING","MPQ":"500","PQ":"2000"}
{"ITEM":"13368","STOCKNO":"VLR-02VF","DSCRPT":"JST HOUSING","MPQ":"500","PQ":"2000"}
{"ITEM":"13369","STOCKNO":"VLR-02VF-R","DSCRPT":"JST HOUSING","MPQ":"500","PQ":"2000"}
{"ITEM":"13370","STOCKNO":"VLR-03V","DSCRPT":"JST HOUSING","MPQ":"500","PQ":"3000"}
{"ITEM":"13371","STOCKNO":"VLR-03V-R","DSCRPT":"JST HOUSING","MPQ":"500","PQ":"3000"}
{"ITEM":"13372","STOCKNO":"VLR-03V-WGA1","DSCRPT":"JST HOUSING","MPQ":"500","PQ":"3000"}
{"ITEM":"13373","STOCKNO":"VLR-04V","DSCRPT":"JST HOUSING","MPQ":"500","PQ":"3000"}
{"ITEM":"13374","STOCKNO":"VLR-04VF","DSCRPT":"JST HOUSING","MPQ":"500","PQ":"3000"}
{"ITEM":"13375","STOCKNO":"VLR-04VN","DSCRPT":"JST HOUSING","MPQ":"500","PQ":"3000"}
{"ITEM":"13376","STOCKNO":"VLR-06V","DSCRPT":"JST HOUSING","MPQ":"500","PQ":"2000"}
{"ITEM":"13377","STOCKNO":"VLR-06V-K","DSCRPT":"JST HOUSING","MPQ":"500","PQ":"2000"}
{"ITEM":"13378","STOCKNO":"VLR-08V","DSCRPT":"JST HOUSING","MPQ":"100","PQ":"1500"}
{"ITEM":"13379","STOCKNO":"VLR-09V","DSCRPT":"JST HOUSING","MPQ":"100","PQ":"2000"}
{"ITEM":"13380","STOCKNO":"VLR-12V","DSCRPT":"JST HOUSING","MPQ":"100","PQ":"1000"}
{"ITEM":"13381","STOCKNO":"VLS-01V","DSCRPT":"JST HOUSING","MPQ":"1000","PQ":"20000"}
{"ITEM":"13382","STOCKNO":"VLS-01V(N)","DSCRPT":"JST HOUSING","MPQ":"1000","PQ":"20000"}
{"ITEM":"13383","STOCKNO":"VLS-02V(N)","DSCRPT":"JST HOUSING","MPQ":"1000","PQ":"20000"}
{"ITEM":"13384","STOCKNO":"VLS-03V(N)","DSCRPT":"JST HOUSING","MPQ":"1000","PQ":"20000"}
{"ITEM":"13385","STOCKNO":"VLS-08V(N)","DSCRPT":"JST HOUSING","MPQ":"1000","PQ":"10000"}
{"ITEM":"13386","STOCKNO":"VLS-12V(N)","DSCRPT":"JST HOUSING","MPQ":"1000","PQ":"7000"}
{"ITEM":"13387","STOCKNO":"VM03B-PASS-NI-TF(SN)","DSCRPT":"JST BASE","MPQ":"500","PQ":"3500"}
{"ITEM":"13388","STOCKNO":"VP-1.25(LF)","DSCRPT":"JST TERMINAL","MPQ":"1000","PQ":"20000"}
{"ITEM":"13389","STOCKNO":"VP-1.25(LF) RED","DSCRPT":"JST TERMINAL","MPQ":"1000","PQ":"20000"}
{"ITEM":"13390","STOCKNO":"VP-1.25(LF)K","DSCRPT":"JST TERMINAL","MPQ":"1000","PQ":"20000"}
{"ITEM":"13391","STOCKNO":"VP-2 K","DSCRPT":"JST TERMINAL","MPQ":"1000","PQ":"20000"}
{"ITEM":"13392","STOCKNO":"VP-5.5","DSCRPT":"JST TERMINAL","MPQ":"1","PQ":"1"}
{"ITEM":"13393","STOCKNO":"VPC-1.25(LF)","DSCRPT":"JST TERMINAL","MPQ":"1000","PQ":"20000"}
{"ITEM":"13394","STOCKNO":"VPC-2 BU","DSCRPT":"JST TERMINAL","MPQ":"1000","PQ":"20000"}
{"ITEM":"13395","STOCKNO":"VRC-02E(LF)","DSCRPT":"JST HOUSING","MPQ":"1000","PQ":"18000"}
{"ITEM":"13396","STOCKNO":"VRC-03D(LF)","DSCRPT":"JST HOUSING","MPQ":"1000","PQ":"18000"}
{"ITEM":"13397","STOCKNO":"VRC-03E","DSCRPT":"JST HOUSING","MPQ":"1000","PQ":"18000"}
{"ITEM":"13398","STOCKNO":"VRC-03E(LF)","DSCRPT":"JST JST 預計停產不可報價1050830-2","MPQ":"1000","PQ":"18000"}
{"ITEM":"13399","STOCKNO":"VRC-04D(LF)","DSCRPT":"JST HOUSING","MPQ":"500","PQ":"9000"}
{"ITEM":"13400","STOCKNO":"VRC-04D-JE","DSCRPT":"JST HOUSING","MPQ":"500","PQ":"9000"}
