{"ITEM":"601","STOCKNO":"06FLZ-RSM2-GB-TB(LF)(SN)","DSCRPT":"JST BASE","MPQ":"2000","PQ":"16000"}
{"ITEM":"602","STOCKNO":"06FLZ-RSM2-TB(LF)(SN)(P)","DSCRPT":"JST BASE","MPQ":"2800","PQ":"25200"}
{"ITEM":"603","STOCKNO":"06FLZ-SM1-TB","DSCRPT":"JST BASE","MPQ":"2000","PQ":"16000"}
{"ITEM":"604","STOCKNO":"06FLZ-SM2-GAN-TB(LF)(SN)(P)(S)","DSCRPT":"JST BASE","MPQ":"2800","PQ":"25200"}
{"ITEM":"605","STOCKNO":"06FLZ-SM2-GB-TB(LF)(SN)","DSCRPT":"JST BASE","MPQ":"2000","PQ":"16000"}
{"ITEM":"606","STOCKNO":"06FLZ-SM2-GB-TB(LF)(SN)(P)","DSCRPT":"JST BASE","MPQ":"2000","PQ":"16000"}
{"ITEM":"607","STOCKNO":"06FLZ-SM2-GD-TB(LF)","DSCRPT":"JST BASE","MPQ":"2000","PQ":"16000"}
{"ITEM":"608","STOCKNO":"06FLZ-SM2-GD-TB(LF)(P)","DSCRPT":"JST BASE","MPQ":"2000","PQ":"16000"}
{"ITEM":"609","STOCKNO":"06FLZ-SM2-TB(LF)(SN)(P)","DSCRPT":"JST BASE","MPQ":"2800","PQ":"25200"}
{"ITEM":"610","STOCKNO":"06FLZT-SM1-TF(H)(LF)(SN)","DSCRPT":"JST BASE","MPQ":"1500","PQ":"12000"}
{"ITEM":"611","STOCKNO":"06FLZT-SM1-TF(LF)(SN)","DSCRPT":"JST BASE","MPQ":"1500","PQ":"12000"}
{"ITEM":"612","STOCKNO":"06FM-1.0BP","DSCRPT":"JST BASE","MPQ":"1000","PQ":"24000"}
{"ITEM":"613","STOCKNO":"06FM-1.0BP-TF(LF)(SN)","DSCRPT":"JST BASE","MPQ":"1000","PQ":"8000"}
{"ITEM":"614","STOCKNO":"06FM-1.0BT","DSCRPT":"JST BASE","MPQ":"1000","PQ":"24000"}
{"ITEM":"615","STOCKNO":"06FM-1.0SP-1.9","DSCRPT":"JST BASE","MPQ":"1000","PQ":"0"}
{"ITEM":"616","STOCKNO":"06FM-1.0SP-1.9-TF(LF)(SN)","DSCRPT":"JST BASE","MPQ":"2500","PQ":"20000"}
{"ITEM":"617","STOCKNO":"06FM-1.0ST(LF)(SN)","DSCRPT":"JST BASE","MPQ":"1000","PQ":"24000"}
{"ITEM":"618","STOCKNO":"06FMN-BMGB-A-TF(LF)(SN)","DSCRPT":"JST BASE","MPQ":"1000","PQ":"8000"}
{"ITEM":"619","STOCKNO":"06FMN-BMT-A-TF(LF)(SN)","DSCRPT":"JST BASE","MPQ":"1000","PQ":"9000"}
{"ITEM":"620","STOCKNO":"06FMN-BMT-A-TFT(LF)(SN)","DSCRPT":"JST BASE","MPQ":"1000","PQ":"9000"}
{"ITEM":"621","STOCKNO":"06FMN-BMT-TF","DSCRPT":"JST BASE","MPQ":"1000","PQ":"8000"}
{"ITEM":"622","STOCKNO":"06FMN-BMTR-A-TBT(LF)(SN)","DSCRPT":"JST BASE","MPQ":"1000","PQ":"8000"}
{"ITEM":"623","STOCKNO":"06FMN-BMTR-TB","DSCRPT":"JST BASE","MPQ":"1000","PQ":"8000"}
{"ITEM":"624","STOCKNO":"06FMN-BMTTN-A-TF(LF)(SN)","DSCRPT":"JST BASE","MPQ":"1000","PQ":"9000"}
{"ITEM":"625","STOCKNO":"06FMN-BMTTN-A-TFT","DSCRPT":"JST BASE","MPQ":"1000","PQ":"0"}
{"ITEM":"626","STOCKNO":"06FMN-BMTTN-A-TFT(LF)(SN)","DSCRPT":"JST BASE","MPQ":"1000","PQ":"9000"}
{"ITEM":"627","STOCKNO":"06FMN-BMTTR-A-TB(LF)(SN)","DSCRPT":"JST BASE","MPQ":"1000","PQ":"9000"}
{"ITEM":"628","STOCKNO":"06FMN-BMTTR-A-TBT(LF)(SN)","DSCRPT":"JST BASE","MPQ":"1000","PQ":"9000"}
{"ITEM":"629","STOCKNO":"06FMN-BTK-A","DSCRPT":"JST BASE","MPQ":"2700","PQ":"0"}
{"ITEM":"630","STOCKNO":"06FMN-BTK-A(LF)(SN)","DSCRPT":"JST BASE","MPQ":"2700","PQ":"27000"}
{"ITEM":"631","STOCKNO":"06FMN-BTRK-A(LF)(SN)","DSCRPT":"JST BASE","MPQ":"2700","PQ":"27000"}
{"ITEM":"632","STOCKNO":"06FMN-BTRK-A(N)(LF)(SN)","DSCRPT":"JST BASE","MPQ":"2700","PQ":"27000"}
{"ITEM":"633","STOCKNO":"06FMN-SMT-A-TF(LF)(SN)","DSCRPT":"JST BASE","MPQ":"2000","PQ":"18000"}
{"ITEM":"634","STOCKNO":"06FMN-STK-A(LF)(SN)","DSCRPT":"JST BASE","MPQ":"1620","PQ":"16200"}
{"ITEM":"635","STOCKNO":"06FMN-STRK-A(N)(LF)(SN)","DSCRPT":"JST BASE","MPQ":"1620","PQ":"16200"}
{"ITEM":"636","STOCKNO":"06FMS-1.0SP-TF","DSCRPT":"JST BASE","MPQ":"2500","PQ":"20000"}
{"ITEM":"637","STOCKNO":"06FMS-1.0SP-TF(LF)(SN)","DSCRPT":"JST BASE","MPQ":"2500","PQ":"20000"}
{"ITEM":"638","STOCKNO":"06FMZ-BT","DSCRPT":"JST BASE","MPQ":"1440","PQ":"11520"}
{"ITEM":"639","STOCKNO":"06FMZ-BT(LF)(SN)","DSCRPT":"JST BASE","MPQ":"1440","PQ":"11520"}
{"ITEM":"640","STOCKNO":"06FMZ-ST(LF)(SN)","DSCRPT":"JST BASE","MPQ":"800","PQ":"6400"}
{"ITEM":"641","STOCKNO":"06FZA-SM1-GAN-ETB(HF)","DSCRPT":"JST BASE","MPQ":"7000","PQ":"84000"}
{"ITEM":"642","STOCKNO":"06FZA-SM1-GAN-TB(HF)","DSCRPT":"JST BASE","MPQ":"7000","PQ":"84000"}
{"ITEM":"643","STOCKNO":"06HR-4K","DSCRPT":"JST HOUSING","MPQ":"1000","PQ":"12000"}
{"ITEM":"644","STOCKNO":"06HR-4K-P-N","DSCRPT":"JST HOUSING","MPQ":"1000","PQ":"12000"}
{"ITEM":"645","STOCKNO":"06HR-6BK-P-N","DSCRPT":"JST HOUSING","MPQ":"1000","PQ":"12000"}
{"ITEM":"646","STOCKNO":"06HR-6S","DSCRPT":"JST HOUSING","MPQ":"1000","PQ":"12000"}
{"ITEM":"647","STOCKNO":"06HR-6S-P-N","DSCRPT":"JST HOUSING","MPQ":"1000","PQ":"12000"}
{"ITEM":"648","STOCKNO":"06JFAT-SAXGDK-H7.5","DSCRPT":"JST HOUSING","MPQ":"378","PQ":"378"}
{"ITEM":"649","STOCKNO":"06JFAT-SAXGF","DSCRPT":"JST HOUSING","MPQ":"0","PQ":"525"}
{"ITEM":"650","STOCKNO":"06JFAT-SAXGF","DSCRPT":"JST HOUSING","MPQ":"525","PQ":"525"}
