{"ITEM":"12751","STOCKNO":"STO-81T-250N","DSCRPT":"JST TERMINAL","MPQ":"4000","PQ":"12000"}
{"ITEM":"12752","STOCKNO":"STO-82T-187N","DSCRPT":"JST TERMINAL","MPQ":"4000","PQ":"12000"}
{"ITEM":"12753","STOCKNO":"STO-82T-187N-8","DSCRPT":"JST TERMINAL","MPQ":"4000","PQ":"12000"}
{"ITEM":"12754","STOCKNO":"STRIPPER 91335","DSCRPT":"JST SPS-61-250家","MPQ":"1","PQ":"1"}
{"ITEM":"12755","STOCKNO":"STRIPPER 91345","DSCRPT":"JST SPS-61-250家","MPQ":"1","PQ":"1"}
{"ITEM":"12756","STOCKNO":"STRIPPER 91980","DSCRPT":"JST 家","MPQ":"1","PQ":"1"}
{"ITEM":"12757","STOCKNO":"STRIPPER HANGER 92560","DSCRPT":"JST SPS-61-250家","MPQ":"1","PQ":"1"}
{"ITEM":"12758","STOCKNO":"STRIPPER PIN 92210","DSCRPT":"JST SPS-61-250家","MPQ":"1","PQ":"1"}
{"ITEM":"12759","STOCKNO":"STS-002GG-P0.6","DSCRPT":"JST TERMINAL","MPQ":"10000","PQ":"50000"}
{"ITEM":"12760","STOCKNO":"STS-002GG-P0.6(LF)(SN)","DSCRPT":"JST TERMINAL","MPQ":"10000","PQ":"50000"}
{"ITEM":"12761","STOCKNO":"STSD-002GG-P0.6(LF)(SN)","DSCRPT":"JST TERMINAL","MPQ":"50000","PQ":"50000"}
{"ITEM":"12762","STOCKNO":"STSH-002GG-P0.6(LF)","DSCRPT":"JST XcTゎ~ ぃi厨基 1050325-2","MPQ":"30000","PQ":"30000"}
{"ITEM":"12763","STOCKNO":"SUHR-02V-S","DSCRPT":"JST HOUSINH","MPQ":"2000","PQ":"40000"}
{"ITEM":"12764","STOCKNO":"SUHR-02V-S-B","DSCRPT":"JST HOUSING","MPQ":"2000","PQ":"40000"}
{"ITEM":"12765","STOCKNO":"SUHR-03V-S","DSCRPT":"JST HOUSING","MPQ":"2000","PQ":"40000"}
{"ITEM":"12766","STOCKNO":"SUHR-03V-S-B","DSCRPT":"JST HOUSING","MPQ":"2000","PQ":"40000"}
{"ITEM":"12767","STOCKNO":"SUHR-04V-S","DSCRPT":"JST HOUSING","MPQ":"2000","PQ":"40000"}
{"ITEM":"12768","STOCKNO":"SUHR-04V-S-B","DSCRPT":"JST HOUSING","MPQ":"2000","PQ":"40000"}
{"ITEM":"12769","STOCKNO":"SUHR-05V-S","DSCRPT":"JST HOUSING","MPQ":"2000","PQ":"40000"}
{"ITEM":"12770","STOCKNO":"SUHR-05V-S-B","DSCRPT":"JST HOUSING","MPQ":"2000","PQ":"40000"}
{"ITEM":"12771","STOCKNO":"SUHR-05V-S-B","DSCRPT":"JST HOUSING","MPQ":"2000","PQ":"40000"}
{"ITEM":"12772","STOCKNO":"SUHR-06V-S","DSCRPT":"JST HOUSING","MPQ":"2000","PQ":"40000"}
{"ITEM":"12773","STOCKNO":"SUHR-06V-S-B","DSCRPT":"JST HOUSING","MPQ":"2000","PQ":"40000"}
{"ITEM":"12774","STOCKNO":"SUHR-08V-S-B","DSCRPT":"JST HOUSING","MPQ":"2000","PQ":"40000"}
{"ITEM":"12775","STOCKNO":"SUHR-10V-S","DSCRPT":"JST HOUSING","MPQ":"1000","PQ":"20000"}
{"ITEM":"12776","STOCKNO":"SUHR-10V-S-B","DSCRPT":"JST HOUSING","MPQ":"1000","PQ":"20000"}
{"ITEM":"12777","STOCKNO":"SUHR-12V-S","DSCRPT":"JST HOUSING","MPQ":"1000","PQ":"20000"}
{"ITEM":"12778","STOCKNO":"SUHR-12V-S-B","DSCRPT":"JST HOUSING","MPQ":"1000","PQ":"20000"}
{"ITEM":"12779","STOCKNO":"SUHR-12V-S-B","DSCRPT":"JST HOUSING","MPQ":"1000","PQ":"20000"}
{"ITEM":"12780","STOCKNO":"SUHR-14V-S","DSCRPT":"JST HOUSING","MPQ":"1000","PQ":"20000"}
{"ITEM":"12781","STOCKNO":"SUHR-14V-S-B","DSCRPT":"JST HOUSING","MPQ":"20000","PQ":"20000"}
{"ITEM":"12782","STOCKNO":"SUHR-16V-S","DSCRPT":"JST HOUSING","MPQ":"1000","PQ":"20000"}
{"ITEM":"12783","STOCKNO":"SUHR-16V-S-B","DSCRPT":"JST HOUSING","MPQ":"1000","PQ":"20000"}
{"ITEM":"12784","STOCKNO":"SUHR-20V-S","DSCRPT":"JST HOUSING","MPQ":"1000","PQ":"20000"}
{"ITEM":"12785","STOCKNO":"SUHR-20V-S","DSCRPT":"JST HOUSING","MPQ":"1000","PQ":"20000"}
{"ITEM":"12786","STOCKNO":"SUHR-20V-S-B","DSCRPT":"JST HOUSING","MPQ":"1000","PQ":"20000"}
{"ITEM":"12787","STOCKNO":"SUHR-20V-S-B","DSCRPT":"JST HOUSING","MPQ":"1000","PQ":"20000"}
{"ITEM":"12788","STOCKNO":"SUPPORTER 73030","DSCRPT":"JST 家","MPQ":"1","PQ":"1"}
{"ITEM":"12789","STOCKNO":"SUPPORTER 73430","DSCRPT":"JST 家","MPQ":"1","PQ":"1"}
{"ITEM":"12790","STOCKNO":"SVA-41T-P1.1","DSCRPT":"JST TERMINAL","MPQ":"3500","PQ":"21000"}
{"ITEM":"12791","STOCKNO":"SVEC-A031GG-M1.0P R4","DSCRPT":"JST TERMINAL","MPQ":"4000","PQ":"16000"}
{"ITEM":"12792","STOCKNO":"SVF-01T-1.5A","DSCRPT":"JST TERMINAL","MPQ":"15000","PQ":"45000"}
{"ITEM":"12793","STOCKNO":"SVF-01T-1.5N","DSCRPT":"JST TERMINAL","MPQ":"4000","PQ":"24000"}
{"ITEM":"12794","STOCKNO":"SVF-01T-1.5S","DSCRPT":"JST TERMINAL","MPQ":"4000","PQ":"24000"}
{"ITEM":"12795","STOCKNO":"SVF-01T-2.36LN","DSCRPT":"JST TERMINAL","MPQ":"5000","PQ":"25000"}
{"ITEM":"12796","STOCKNO":"SVF-01T-2.36N","DSCRPT":"JST TERMINAL","MPQ":"15000","PQ":"45000"}
{"ITEM":"12797","STOCKNO":"SVF-41T-P2.0","DSCRPT":"JST TERMINAL","MPQ":"1","PQ":"0"}
{"ITEM":"12798","STOCKNO":"SVF-41T-P2.0A","DSCRPT":"JST TERMINAL","MPQ":"3000","PQ":"15000"}
{"ITEM":"12799","STOCKNO":"SVF-42T-P2.0","DSCRPT":"JST TERMINAL","MPQ":"2000","PQ":"10000"}
{"ITEM":"12800","STOCKNO":"SVF-61T-2.0","DSCRPT":"JST TERMINAL","MPQ":"2000","PQ":"10000"}
