{"ITEM":"7751","STOCKNO":"FN2-4","DSCRPT":"JST 轉JIS認證料號RBC2-4(NJ)    1070131-1","MPQ":"500","PQ":"10000"}
{"ITEM":"7752","STOCKNO":"FN2-M4","DSCRPT":"JST TERMINAL","MPQ":"500","PQ":"10000"}
{"ITEM":"7753","STOCKNO":"FN2-M5 BL","DSCRPT":"JST TERMINAL","MPQ":"500","PQ":"30000"}
{"ITEM":"7754","STOCKNO":"FN2-P4","DSCRPT":"JST TERMINAL","MPQ":"500","PQ":"10000"}
{"ITEM":"7755","STOCKNO":"FN5.5-4","DSCRPT":"JST TERMINAL1071109-2轉RBC535-4 Y(NJ)","MPQ":"0","PQ":"0"}
{"ITEM":"7756","STOCKNO":"FN5.5-S4","DSCRPT":"JST TERMINAL","MPQ":"500","PQ":"8000"}
{"ITEM":"7757","STOCKNO":"FNC-1.25","DSCRPT":"JST TERMINAL","MPQ":"500","PQ":"10000"}
{"ITEM":"7758","STOCKNO":"FNC-2","DSCRPT":"JST TERMINAL+BU","MPQ":"500","PQ":"10000"}
{"ITEM":"7759","STOCKNO":"FNC-2 BU","DSCRPT":"JST TERMINAL","MPQ":"500","PQ":"10000"}
{"ITEM":"7760","STOCKNO":"FNC-5.5 YE","DSCRPT":"JST TERMINAL","MPQ":"200","PQ":"4000"}
{"ITEM":"7761","STOCKNO":"FNCW-1.25 R.CLR","DSCRPT":"JST TERMINAL","MPQ":"500","PQ":"10000"}
{"ITEM":"7762","STOCKNO":"FNCW-2 B.CLR","DSCRPT":"JST TERMINAL","MPQ":"500","PQ":"10000"}
{"ITEM":"7763","STOCKNO":"FND1.25-4LS R.CLR","DSCRPT":"JST TERMINAL","MPQ":"1000","PQ":"20000"}
{"ITEM":"7764","STOCKNO":"FND2-4LS B.CLR","DSCRPT":"JST TERMINAL","MPQ":"1000","PQ":"20000"}
{"ITEM":"7765","STOCKNO":"FND5.5-4LS Y.CLR","DSCRPT":"JST TERMINAL","MPQ":"500","PQ":"10000"}
{"ITEM":"7766","STOCKNO":"FNGS4-2.5","DSCRPT":"JST TERMINAL","MPQ":"20000","PQ":"20000"}
{"ITEM":"7767","STOCKNO":"FNGS4-6","DSCRPT":"JST TERMINAL","MPQ":"10000","PQ":"10000"}
{"ITEM":"7768","STOCKNO":"FNGS4S-2.5","DSCRPT":"JST TERMINAL","MPQ":"1000","PQ":"20000"}
{"ITEM":"7769","STOCKNO":"FNGS5-2.5","DSCRPT":"JST TERMINAL","MPQ":"16000","PQ":"16000"}
{"ITEM":"7770","STOCKNO":"FNGS5-6","DSCRPT":"JST TERMINAL","MPQ":"10000","PQ":"10000"}
{"ITEM":"7771","STOCKNO":"FNP-5.5 CLR","DSCRPT":"JST TERMINAL","MPQ":"250","PQ":"5000"}
{"ITEM":"7772","STOCKNO":"FNP-5.5 YE","DSCRPT":"JST TERMINAL","MPQ":"250","PQ":"5000"}
{"ITEM":"7773","STOCKNO":"FOXP-10K","DSCRPT":"JST HOUSING","MPQ":"500","PQ":"2500"}
{"ITEM":"7774","STOCKNO":"FOXS-10K","DSCRPT":"JST HOUSING","MPQ":"500","PQ":"2500"}
{"ITEM":"7775","STOCKNO":"FPS-187","DSCRPT":"JST HOUSING","MPQ":"12000","PQ":"12000"}
{"ITEM":"7776","STOCKNO":"FPS-187-E","DSCRPT":"JST HOUSOING","MPQ":"10000","PQ":"10000"}
{"ITEM":"7777","STOCKNO":"FPS-187-K","DSCRPT":"JST HOUSING","MPQ":"10000","PQ":"10000"}
{"ITEM":"7778","STOCKNO":"FPS-250","DSCRPT":"JST HOUSING","MPQ":"500","PQ":"7000"}
{"ITEM":"7779","STOCKNO":"FPS-250-K","DSCRPT":"JST HOUSING","MPQ":"500","PQ":"10000"}
{"ITEM":"7780","STOCKNO":"FPS-250-R","DSCRPT":"JST HOUSING","MPQ":"500","PQ":"10000"}
{"ITEM":"7781","STOCKNO":"FT1.25-M3(MK)","DSCRPT":"JST TERMINAL","MPQ":"1000","PQ":"20000"}
{"ITEM":"7782","STOCKNO":"FTC-1.25","DSCRPT":"JST TERMINAL","MPQ":"1000","PQ":"16000"}
{"ITEM":"7783","STOCKNO":"FV0.5-2 CLR","DSCRPT":"JST TERMINAL","MPQ":"25000","PQ":"25000"}
{"ITEM":"7784","STOCKNO":"FV0.5-3","DSCRPT":"JST TERMINAL","MPQ":"1000","PQ":"25000"}
{"ITEM":"7785","STOCKNO":"FV0.5-3 CLR","DSCRPT":"JST TERMINAL","MPQ":"1000","PQ":"25000"}
{"ITEM":"7786","STOCKNO":"FV0.5-3(LF)","DSCRPT":"JST TERMINAL","MPQ":"1000","PQ":"25000"}
{"ITEM":"7787","STOCKNO":"FV0.5-3(LF) YE","DSCRPT":"JST TERMINAL","MPQ":"1000","PQ":"25000"}
{"ITEM":"7788","STOCKNO":"FV0.5-4(LF)","DSCRPT":"JST TERMINAL","MPQ":"1000","PQ":"25000"}
{"ITEM":"7789","STOCKNO":"FV0.5-4(LF) YE","DSCRPT":"JST TERMINAL","MPQ":"1000","PQ":"25000"}
{"ITEM":"7790","STOCKNO":"FV0.5-4(LF)K","DSCRPT":"JST TERMINAL","MPQ":"1000","PQ":"25000"}
{"ITEM":"7791","STOCKNO":"FV0.5-5(LF)","DSCRPT":"JST TERMINAL","MPQ":"1000","PQ":"25000"}
{"ITEM":"7792","STOCKNO":"FV1.25-10 RD","DSCRPT":"JST TERMINAL","MPQ":"1000","PQ":"16000"}
{"ITEM":"7793","STOCKNO":"FV1.25-2AF(LF)","DSCRPT":"JST TERMINAL","MPQ":"1000","PQ":"20000"}
{"ITEM":"7794","STOCKNO":"FV1.25-3","DSCRPT":"JST TERMINL","MPQ":"1000","PQ":"1000"}
{"ITEM":"7795","STOCKNO":"FV1.25-3(LF)","DSCRPT":"JST TERMINAL","MPQ":"1000","PQ":"20000"}
{"ITEM":"7796","STOCKNO":"FV1.25-3.7 TOR(LF)","DSCRPT":"JST TERMINAL","MPQ":"1000","PQ":"10000"}
{"ITEM":"7797","STOCKNO":"FV1.25-3.7(LF)","DSCRPT":"JST TERMINAL","MPQ":"1000","PQ":"20000"}
{"ITEM":"7798","STOCKNO":"FV1.25-4","DSCRPT":"JST 改RBA1.25-4 (LF)(NJ)","MPQ":"1000","PQ":"20000"}
{"ITEM":"7799","STOCKNO":"FV1.25-4(LF)","DSCRPT":"JST 改RBA1.25-4 (LF)(NJ)","MPQ":"1000","PQ":"20000"}
{"ITEM":"7800","STOCKNO":"FV1.25-4-TOR(LF)","DSCRPT":"JST TERMINAL","MPQ":"1000","PQ":"10000"}
